
            {
                "id": 91,
                "chat_id": -1003090735869,
                "status": "StatusSession.COMPLETED",
                "state": {
                    "current_state": "GameState.WAIT_ANSWER"
                },
                "players": [
                    {
                        "is_active": true,
                        "is_ready": false,
                        "is_captain": false,
                        "user_tg": {
                            "username_tg": "ALimDzen",
                            "id_tg": 905669710
                        }
                    },
                    {
                        "is_active": true,
                        "is_ready": false,
                        "is_captain": true,
                        "user_tg": {
                            "username_tg": "courvuisier",
                            "id_tg": 1278888559
                        }
                    }
                ],
                "experts_score": 3,
                "bot_score": 6
            }
